{
  "repositoryName": "jgit",
  "repositoryWebURL": "https://github.com/eclipse/jgit.git",
  "filePath": "org.eclipse.jgit/src/org/eclipse/jgit/transport/UploadPack.java",
  "functionName": "sendPack",
  "functionKey": "org.eclipse.jgit/src/org.eclipse.jgit.transport.UploadPack#sendPack(boolean, PackStatistics.Accumulator, Collection, List)",
  "functionStartLine": 1965,
  "blockType": "IF_STATEMENT",
  "blockKey": "org.eclipse.jgit/src/org.eclipse.jgit.transport.UploadPack#sendPack(boolean, PackStatistics.Accumulator, Collection, List)$if(2025-2026)",
  "blockStartLine": 2025,
  "blockEndLine": 2026,
  "startCommitId": "bd1a82502680b5de5bf86f6c4470185fd1602386",
  "expectedChanges": [
    {
      "parentCommitId": "bb99ec0aa00aab6d9f60e4d35c93d20bd614e4dc",
      "commitId": "9fbce904e6471b49668457caa4c0c2d4131a0fb5",
      "commitTime": 1280344428,
      "changeType": "introduced",
      "elementFileBefore": "org.eclipse.jgit/src/org/eclipse/jgit/transport/UploadPack.java",
      "elementNameBefore": "org.eclipse.jgit/src/org.eclipse.jgit.transport.UploadPack#sendPack()$if(585-586)",
      "elementFileAfter": "org.eclipse.jgit/src/org/eclipse/jgit/transport/UploadPack.java",
      "elementNameAfter": "org.eclipse.jgit/src/org.eclipse.jgit.transport.UploadPack#sendPack()$if(585-586)",
      "comment": "new block"
    }
  ]
}