{
  "repositoryName": "jgit",
  "repositoryWebURL": "https://github.com/eclipse/jgit.git",
  "filePath": "org.eclipse.jgit/src/org/eclipse/jgit/api/RebaseCommand.java",
  "functionName": "call",
  "functionKey": "org.eclipse.jgit/src/org.eclipse.jgit.api.RebaseCommand#call()",
  "functionStartLine": 254,
  "blockType": "IF_STATEMENT",
  "blockKey": "org.eclipse.jgit/src/org.eclipse.jgit.api.RebaseCommand#call()$if(359-363)",
  "blockStartLine": 359,
  "blockEndLine": 363,
  "startCommitId": "bd1a82502680b5de5bf86f6c4470185fd1602386",
  "expectedChanges": [
    {
      "parentCommitId": "e649287502407e10c89de03e82cc0de855e01dcf",
      "commitId": "c3873b584f81bc5be3fdea53e9e0e76271a9a854",
      "commitTime": 1383225740,
      "changeType": "body change",
      "elementFileBefore": "org.eclipse.jgit/src/org/eclipse/jgit/api/RebaseCommand.java",
      "elementNameBefore": "org.eclipse.jgit/src/org.eclipse.jgit.api.RebaseCommand#call()$if(271-294)",
      "elementFileAfter": "org.eclipse.jgit/src/org/eclipse/jgit/api/RebaseCommand.java",
      "elementNameAfter": "org.eclipse.jgit/src/org.eclipse.jgit.api.RebaseCommand#call()$if(269-273)"
    },
    {
      "parentCommitId": "bba74ba2e0af10db4d75258819ca0a1b4307e377",
      "commitId": "0e9f1cf57dac274f92a6db38197e14b55b3277af",
      "commitTime": 1363473133,
      "changeType": "body change",
      "elementFileBefore": "org.eclipse.jgit/src/org/eclipse/jgit/api/RebaseCommand.java",
      "elementNameBefore": "org.eclipse.jgit/src/org.eclipse.jgit.api.RebaseCommand#call()$if(266-289)",
      "elementFileAfter": "org.eclipse.jgit/src/org/eclipse/jgit/api/RebaseCommand.java",
      "elementNameAfter": "org.eclipse.jgit/src/org.eclipse.jgit.api.RebaseCommand#call()$if(271-294)"
    },
    {
      "parentCommitId": "8b06c46e301e4b9df4b2f47d1e67fb4ab319ded5",
      "commitId": "257f3fe4a1b9e450b2f665b5f0ed09a3ab3839b9",
      "commitTime": 1354001680,
      "changeType": "body change",
      "elementFileBefore": "org.eclipse.jgit/src/org/eclipse/jgit/api/RebaseCommand.java",
      "elementNameBefore": "org.eclipse.jgit/src/org.eclipse.jgit.api.RebaseCommand#call()$if(266-289)",
      "elementFileAfter": "org.eclipse.jgit/src/org/eclipse/jgit/api/RebaseCommand.java",
      "elementNameAfter": "org.eclipse.jgit/src/org.eclipse.jgit.api.RebaseCommand#call()$if(266-289)"
    },
    {
      "parentCommitId": "9051af3c4d870e255428b814b6b31cf7506f6ac0",
      "commitId": "84fb2b59d11418d2fa753d27de11775ddc18adde",
      "commitTime": 1353339653,
      "changeType": "introduced",
      "elementFileBefore": "org.eclipse.jgit/src/org/eclipse/jgit/api/RebaseCommand.java",
      "elementNameBefore": "org.eclipse.jgit/src/org.eclipse.jgit.api.RebaseCommand#call()$if(259-282)",
      "elementFileAfter": "org.eclipse.jgit/src/org/eclipse/jgit/api/RebaseCommand.java",
      "elementNameAfter": "org.eclipse.jgit/src/org.eclipse.jgit.api.RebaseCommand#call()$if(259-282)",
      "comment": "new block"
    }
  ]
}