{
  "repositoryName": "okhttp",
  "repositoryWebURL": "https://github.com/square/okhttp.git",
  "filePath": "okhttp/src/main/java/okhttp3/internal/connection/RealConnection.java",
  "functionName": "connect",
  "functionKey": "okhttp/src/main/java/okhttp3.internal.connection.RealConnection#connect(int, int, int, int, boolean, Call, EventListener)",
  "functionStartLine": 130,
  "blockType": "IF_STATEMENT",
  "blockKey": "okhttp/src/main/java/okhttp3.internal.connection.RealConnection#connect(int, int, int, int, boolean, Call, EventListener)$if(201-205)",
  "blockStartLine": 201,
  "blockEndLine": 205,
  "startCommitId": "5224f3045ba9b171fce521777edf389f9206173c",
  "expectedChanges": [
    {
      "parentCommitId": "5c7257d8d1c07b66cb7b14832bc0d16b88abcfb5",
      "commitId": "8331b2d75a51631bee622daf2175854fe49ce29a",
      "commitTime": 1483378611,
      "changeType": "introduced",
      "elementFileBefore": "okhttp/src/main/java/okhttp3/internal/connection/RealConnection.java",
      "elementNameBefore": "okhttp/src/main/java/okhttp3.internal.connection.RealConnection#connect(int, int, int, List, boolean)$if(172-176)",
      "elementFileAfter": "okhttp/src/main/java/okhttp3/internal/connection/RealConnection.java",
      "elementNameAfter": "okhttp/src/main/java/okhttp3.internal.connection.RealConnection#connect(int, int, int, List, boolean)$if(172-176)",
      "comment": "new block"
    }
  ]
}