{
  "repositoryName" : "jgit",
  "repositoryWebURL" : "https://github.com/eclipse/jgit.git",
  "startCommitId" : "bd1a82502680b5de5bf86f6c4470185fd1602386",
  "filePath" : "org.eclipse.jgit/src/org/eclipse/jgit/transport/UploadPack.java",
  "attributeName" : "clientRequestedV2",
  "attributeKey" : "org.eclipse.jgit/src/org.eclipse.jgit.transport.UploadPack@clientRequestedV2:boolean(252)",
  "attributeDeclarationLine" : 252,
  "expectedChanges" : [ {
    "parentCommitId" : "75b07036928f4ef73e9a217bd7c898457e9c7120",
    "commitId" : "2661bc081340ae83d2a2ecba11994d3e8d56586b",
    "commitTime" : 1524266260,
    "changeType" : "introduced",
    "elementFileBefore" : "org.eclipse.jgit/src/org/eclipse/jgit/transport/UploadPack.java",
    "elementNameBefore" : "org.eclipse.jgit/src/org.eclipse.jgit.transport.UploadPack@(private)clientRequestedV2:boolean(252)",
    "elementFileAfter" : "org.eclipse.jgit/src/org/eclipse/jgit/transport/UploadPack.java",
    "elementNameAfter" : "org.eclipse.jgit/src/org.eclipse.jgit.transport.UploadPack@(private)clientRequestedV2:boolean(252)",
    "comment" : "new attribute"
  } ]
}