{
  "repositoryName" : "checkstyle\\checkstyle",
  "repositoryWebURL" : "https://github.com/checkstyle/checkstyle.git",
  "filePath" : "src/main/java/com/puppycrawl/tools/checkstyle/utils/CommonUtils.java",
  "functionName" : "createPattern",
  "functionKey" : "src/main/java/com.puppycrawl.tools.checkstyle.utils.CommonUtils#createPattern(String, int)",
  "functionStartLine" : 104,
  "variableName" : "flags",
  "variableKey" : "src/main/java/com.puppycrawl.tools.checkstyle.utils.CommonUtils#createPattern(String, int)$flags(104)",
  "variableStartLine" : 104,
  "startCommitId" : "119fd4fb33bef9f5c66fc950396669af842c21a3",
  "expectedChanges" : [ {
    "parentCommitId" : "2ba55edc4e35866afbb154e3ea03cf03e56ab9bc",
    "commitId" : "f2c6263e151e8a7300755b36fbb41511c0a0cca1",
    "commitTime" : 1446178343,
    "changeType" : "introduced",
    "elementFileBefore" : "src/main/java/com/puppycrawl/tools/checkstyle/utils/CommonUtils.java",
    "elementNameBefore" : "src/main/java/com.puppycrawl.tools.checkstyle.utils.CommonUtils#createPattern(String, int)$flags:int(201)",
    "elementFileAfter" : "src/main/java/com/puppycrawl/tools/checkstyle/utils/CommonUtils.java",
    "elementNameAfter" : "src/main/java/com.puppycrawl.tools.checkstyle.utils.CommonUtils#createPattern(String, int)$flags:int(201)",
    "comment" : "Extract Method public createPattern(pattern String, flags int) : Pattern extracted from public createPattern(pattern String) : Pattern in class com.puppycrawl.tools.checkstyle.utils.CommonUtils"
  } ]
}