{
  "repositoryName" : "apache\\commons-lang",
  "repositoryWebURL" : "https://github.com/apache/commons-lang.git",
  "filePath" : "src/main/java/org/apache/commons/lang3/time/DurationFormatUtils.java",
  "functionName" : "formatPeriod",
  "functionKey" : "src/main/java/org.apache.commons.lang3.time.DurationFormatUtils#formatPeriod(long, long, String, boolean, TimeZone)",
  "functionStartLine" : 279,
  "variableName" : "years",
  "variableKey" : "years : int",
  "variableStartLine" : 306,
  "startCommitName" : "a36c903d4f1065bc59f5e6d2bb0f9d92a5e71d83",
  "branchName" : null,
  "expectedResult" : {
    "177d40989f45197fd9f9669f4eeb6033b73bc16e" : "added"
  }
}