{
  "repositoryName" : "spring-projects\\spring-framework",
  "repositoryWebURL" : "https://github.com/spring-projects/spring-framework.git",
  "filePath" : "spring-context/src/main/java/org/springframework/context/annotation/ConfigurationClassParser.java",
  "functionName" : "doProcessConfigurationClass",
  "functionKey" : "spring-context/src/main/java/org.springframework.context.annotation.ConfigurationClassParser#doProcessConfigurationClass(ConfigurationClass, SourceClass)",
  "functionStartLine" : 261,
  "variableName" : "importResource",
  "variableKey" : "importResource : AnnotationAttributes",
  "variableStartLine" : 306,
  "startCommitName" : "b325c74216fd9564a36602158fa1269e2e832874",
  "branchName" : null,
  "expectedResult" : {
    "ee36c80ca961a5b2af233cd26a5483d57939c0af" : "added"
  }
}